pydeco.py
py_deco-0.1.0.dist-info/WHEEL
py_deco-0.1.0.dist-info/METADATA
py_deco-0.1.0.dist-info/RECORD
