Metadata-Version: 2.1
Name: py-deco
Version: 0.1.0
Summary: Python decorators
Home-page: https://github.com/quelhasu/pydeco
Author: ugo-quelhas
Author-email: ugo.quelhas@edu.devinci.fr
Requires-Python: >=3.6,<4.0
Classifier: Programming Language :: Python :: 3
Classifier: Programming Language :: Python :: 3.6
Classifier: Programming Language :: Python :: 3.7
Classifier: Programming Language :: Python :: 3.8
Classifier: Programming Language :: Python :: 3.9
Requires-Dist: forbiddenfruit (>=0.1.4,<0.2.0)
Project-URL: Repository, https:///github.com/quelhasu/pydeco
